keteparaha/email_client.py
keteparaha/browser.py
keteparaha/__init__.py
keteparaha/flow.py
keteparaha/page.py
keteparaha/expectations.py
keteparaha-0.0.24.dist-info/top_level.txt
keteparaha-0.0.24.dist-info/RECORD
keteparaha-0.0.24.dist-info/DESCRIPTION.rst
keteparaha-0.0.24.dist-info/METADATA
keteparaha-0.0.24.dist-info/metadata.json
keteparaha-0.0.24.dist-info/WHEEL
