Metadata-Version: 2.0
Name: keteparaha
Version: 0.0.24
Summary: Keteparaha is a tool for testing modern JS heavy websites
Home-page: https://github.com/aychedee/keteparaha/
Author: Hansel Dunlop
Author-email: hansel@interpretthis.org
License: MIT
Platform: UNKNOWN
Requires-Dist: imapclient
Requires-Dist: pyvirtualdisplay
Requires-Dist: selenium
